cert_session/__init__.py
tests/__init__.py
tests/conftest.py
tests/test_cert_session.py
tests/test_conf.py
cert_session-0.0.3.dist-info/METADATA
cert_session-0.0.3.dist-info/WHEEL
cert_session-0.0.3.dist-info/top_level.txt
cert_session-0.0.3.dist-info/RECORD
