Metadata-Version: 2.1
Name: cert-session
Version: 0.0.3
Summary: 'requests' session that appends custom certificate authority
Home-page: https://github.com/lsiden/cert_session
Author: Lawrence Siden
Author-email: lsiden@gmail.com
License: UNKNOWN
Platform: UNKNOWN
Classifier: Programming Language :: Python :: 3
Classifier: License :: OSI Approved :: MIT License
Classifier: Operating System :: OS Independent
Requires-Python: >=3.6
Requires-Dist: requests
